labelbigquery/__init__.py
labelbigquery/fetch_and_write_rows.py
labelbigquery/load_data_to_big_query.py
labelbigquery/make_dataset_and_data_rows.py
labelbigquery-0.1.0.dist-info/LICENSE
labelbigquery-0.1.0.dist-info/METADATA
labelbigquery-0.1.0.dist-info/WHEEL
labelbigquery-0.1.0.dist-info/top_level.txt
labelbigquery-0.1.0.dist-info/RECORD
