Metadata-Version: 2.1
Name: labelbigquery
Version: 0.1.0
Summary: Labelbox Connector for BigQuery
Home-page: https://labelbox.com
Author: Labelbox
Author-email: ecosystem+bigquery@labelbox.com
License: UNKNOWN
Keywords: labelbox,bigquery,labelbigquery
Platform: UNKNOWN
License-File: LICENSE
Requires-Dist: labelbox
Requires-Dist: google-cloud-bigquery
